platformer/__init__.py
platformer/game.py
platformer/assets/Background/Blue.png
platformer/assets/Background/Brown.png
platformer/assets/Background/Gray.png
platformer/assets/Background/Green.png
platformer/assets/Background/Pink.png
platformer/assets/Background/Purple.png
platformer/assets/Background/Yellow.png
platformer/assets/Terrain/Terrain.png
platformer/assets/Traps/Fire/hit.png
platformer/assets/Traps/Fire/off.png
platformer/assets/Traps/Fire/on.png
PyGame_Platformer_Fin-4.0.dist-info/LICENSE.txt
PyGame_Platformer_Fin-4.0.dist-info/METADATA
PyGame_Platformer_Fin-4.0.dist-info/WHEEL
PyGame_Platformer_Fin-4.0.dist-info/entry_points.txt
PyGame_Platformer_Fin-4.0.dist-info/top_level.txt
PyGame_Platformer_Fin-4.0.dist-info/RECORD
